pedalboard_pluginary/__init__.py
pedalboard_pluginary/__main__.py
pedalboard_pluginary/_version.py
pedalboard_pluginary/constants.py
pedalboard_pluginary/core.py
pedalboard_pluginary/data.py
pedalboard_pluginary/exceptions.py
pedalboard_pluginary/models.py
pedalboard_pluginary/progress.py
pedalboard_pluginary/protocols.py
pedalboard_pluginary/py.typed
pedalboard_pluginary/retry.py
pedalboard_pluginary/scan_single.py
pedalboard_pluginary/scanner_clean.py
pedalboard_pluginary/scanner_isolated.py
pedalboard_pluginary/serialization.py
pedalboard_pluginary/timeout.py
pedalboard_pluginary/types.py
pedalboard_pluginary/utils.py
pedalboard_pluginary/cache/__init__.py
pedalboard_pluginary/cache/json_backend.py
pedalboard_pluginary/cache/migration.py
pedalboard_pluginary/cache/sqlite_backend.py
pedalboard_pluginary/resources/default_ignores.json
pedalboard_pluginary-1.1.6.dist-info/METADATA
pedalboard_pluginary-1.1.6.dist-info/WHEEL
pedalboard_pluginary-1.1.6.dist-info/entry_points.txt
pedalboard_pluginary-1.1.6.dist-info/licenses/AUTHORS.md
pedalboard_pluginary-1.1.6.dist-info/licenses/LICENSE.txt
pedalboard_pluginary-1.1.6.dist-info/RECORD
