Metadata-Version: 2.4
Name: pedalboard-pluginary
Version: 1.1.6
Summary: A plugin scanner for Pedalboard
Project-URL: Documentation, https://github.com/twardoch/pedalboard-pluginary#readme
Project-URL: Source, https://github.com/twardoch/pedalboard-pluginary
Project-URL: Tracker, https://github.com/twardoch/pedalboard-pluginary/issues
Author-email: Adam Twardoch <adam@twardoch.com>
License: Apache-2.0
License-File: AUTHORS.md
License-File: LICENSE.txt
Classifier: Development Status :: 4 - Beta
Classifier: Intended Audience :: Developers
Classifier: License :: OSI Approved :: Apache Software License
Classifier: Operating System :: OS Independent
Classifier: Programming Language :: Python
Classifier: Programming Language :: Python :: 3
Classifier: Programming Language :: Python :: 3.9
Classifier: Programming Language :: Python :: 3.10
Classifier: Programming Language :: Python :: 3.11
Classifier: Topic :: Multimedia :: Sound/Audio
Classifier: Topic :: Software Development :: Libraries :: Python Modules
Requires-Python: >=3.9
Requires-Dist: fire>=0.5.0
Requires-Dist: pedalboard>=0.8.7
Requires-Dist: python-benedict>=0.33.0
Requires-Dist: pyyaml>=6.0.1
Requires-Dist: tqdm>=4.60.0
Requires-Dist: typing-extensions>=4.0.0; python_version < '3.11'
Provides-Extra: dev
Requires-Dist: black>=24.1.1; extra == 'dev'
Requires-Dist: build>=0.10.0; extra == 'dev'
Requires-Dist: flake8>=7.0.0; extra == 'dev'
Requires-Dist: isort>=5.13.2; extra == 'dev'
Requires-Dist: mypy>=1.8.0; extra == 'dev'
Requires-Dist: psutil>=5.9.0; extra == 'dev'
Requires-Dist: pyinstaller>=5.0.0; extra == 'dev'
Requires-Dist: pytest-cov>=4.1.0; extra == 'dev'
Requires-Dist: pytest>=7.4.4; extra == 'dev'
Requires-Dist: twine>=4.0.0; extra == 'dev'
